./.ignore
./.python-version
./PKG-INFO
./README.md
./pyproject.toml
./uv.lock
./vxsched.py
./tests/test_vxsched.py
vxsched-20260121.dist-info/METADATA
vxsched-20260121.dist-info/WHEEL
vxsched-20260121.dist-info/entry_points.txt
vxsched-20260121.dist-info/RECORD
