Metadata-Version: 2.4
Name: vxsched
Version: 20260121
Summary: 基于事件驱动的轻量级任务调度器
Author-email: vex1023 <vex1023@qq.com>
License: MIT
Classifier: Development Status :: 4 - Beta
Classifier: Intended Audience :: Developers
Classifier: License :: OSI Approved :: MIT License
Classifier: Programming Language :: Python :: 3
Classifier: Programming Language :: Python :: 3.10
Classifier: Programming Language :: Python :: 3.11
Classifier: Programming Language :: Python :: 3.12
Classifier: Programming Language :: Python :: 3.13
Classifier: Programming Language :: Python :: 3.14
Classifier: Topic :: Software Development :: Libraries :: Python Modules
Classifier: Topic :: System :: Monitoring
Requires-Python: >=3.10
Requires-Dist: pydantic>=2.0.0
Requires-Dist: vxutils>=20260121
